bisearch.py
bisearch-0.1.2.dist-info/METADATA
bisearch-0.1.2.dist-info/WHEEL
bisearch-0.1.2.dist-info/license.txt
bisearch-0.1.2.dist-info/top_level.txt
bisearch-0.1.2.dist-info/RECORD
